sunyan/__init__.py
sunyan/__version__.py
sunyan/decorator/__init__.py
sunyan/decorator/runtime.py
sunyan/decorator/typeassert.py
sunyan/message/__init__.py
sunyan/message/loading.py
sunyan/message/message.py
sunyan-1.1.0.dist-info/METADATA
sunyan-1.1.0.dist-info/RECORD
sunyan-1.1.0.dist-info/WHEEL
sunyan-1.1.0.dist-info/top_level.txt
