Metadata-Version: 2.1
Name: sunyan
Version: 1.1.0
Summary: My short description for my project.
Home-page: https://github.com/SunYanCN/sunyan
Author: sunyan
Author-email: 920425710@qq.com
License: MIT
Platform: UNKNOWN
Classifier: License :: OSI Approved :: MIT License
Classifier: Programming Language :: Python
Classifier: Programming Language :: Python :: 3
Classifier: Programming Language :: Python :: 3.5
Classifier: Programming Language :: Python :: Implementation :: CPython
Classifier: Programming Language :: Python :: Implementation :: PyPy
Requires-Python: >=3.5.0
